xremap/dsl.py
xremap-0.1.0.data/scripts/xremap-python
xremap-0.1.0.dist-info/LICENSE
xremap-0.1.0.dist-info/METADATA
xremap-0.1.0.dist-info/WHEEL
xremap-0.1.0.dist-info/top_level.txt
xremap-0.1.0.dist-info/RECORD
