Metadata-Version: 2.1
Name: xremap
Version: 0.1.0
Summary: Generate xremap config from Python
Home-page: https://github.com/xremap/xremap-python
Author: Takashi Kokubun
Author-email: takashikkbn@gmail.com
License: UNKNOWN
Platform: UNKNOWN
License-File: LICENSE
Requires-Dist: pyyaml
